NoteShrinker/__init__.py
NoteShrinker/cli.py
NoteShrinker/noteshrinker.py
NoteShrinker/noteshrinker_helpers.py
NoteShrinker-0.2.0.dist-info/DESCRIPTION.rst
NoteShrinker-0.2.0.dist-info/METADATA
NoteShrinker-0.2.0.dist-info/RECORD
NoteShrinker-0.2.0.dist-info/WHEEL
NoteShrinker-0.2.0.dist-info/entry_points.txt
NoteShrinker-0.2.0.dist-info/metadata.json
NoteShrinker-0.2.0.dist-info/top_level.txt
