Metadata-Version: 2.0
Name: NoteShrinker
Version: 0.2.0
Summary: Smart shrinking of the size and color palette of images
Home-page: https://github.com/ghandic/NoteShrinker
Author: Andrew Challis
Author-email: andrewchallis@hotmail.com
License: MIT
Keywords: noteshrink
Platform: UNKNOWN
Classifier: Development Status :: 3 - Alpha
Classifier: License :: OSI Approved :: MIT License
Classifier: Programming Language :: Python :: 3.6
Classifier: Programming Language :: Python :: 3.7
Classifier: Topic :: Multimedia :: Graphics
Requires-Dist: numpy (>=1.1.0)
Requires-Dist: pillow
Requires-Dist: scipy
